Workbook

Sheet Summary
A1: Second Coat: 12-month summary
A2: Change the yellow cells on the Assumptions tab and everything here updates.
A4: Metric | B4: Value
A5: Demos built (12 months) | B5: =Model!N4
A6: Paid clients (12 months) | B6: =Model!N5
A7: Total revenue (12 months) | B7: =Model!N14
A8: Total profit (12 months) | B8: =Model!N19
A9: Hours worked (12 months) | B9: =Model!N21
A10: Effective £ per hour | B10: =Model!N22
A11: Care clients at month 12 | B11: =Model!M12
A12: Monthly recurring revenue at month 12 | B12: =Model!M23
A13: Recurring revenue run-rate (× 12) | B13: =Model!M23*12
A14: Demos needed per paid client | B14: =IF(Assumptions!$B$8>0,1/Assumptions!$B$8,0)
A17: Sensitivity: 12-month profit by conversion rate (other assumptions held)
A18: Conversion | B18: Paid clients | C18: Approx. 12-month project revenue
A19: 0.05 | B19: =Model!N4*A19 | C19: =B19*((1-Assumptions!$B$9)*Assumptions!$B$10+Assumptions!$B$9*Assumptions!$B$11)
A20: 0.1 | B20: =Model!N4*A20 | C20: =B20*((1-Assumptions!$B$9)*Assumptions!$B$10+Assumptions!$B$9*Assumptions!$B$11)
A21: 0.125 | B21: =Model!N4*A21 | C21: =B21*((1-Assumptions!$B$9)*Assumptions!$B$10+Assumptions!$B$9*Assumptions!$B$11)
A22: 0.2 | B22: =Model!N4*A22 | C22: =B22*((1-Assumptions!$B$9)*Assumptions!$B$10+Assumptions!$B$9*Assumptions!$B$11)
A23: 0.3 | B23: =Model!N4*A23 | C23: =B23*((1-Assumptions!$B$9)*Assumptions!$B$10+Assumptions!$B$9*Assumptions!$B$11)
A25: The sensitivity table excludes care revenue, so it understates totals. Use it to compare conversion scenarios.

Sheet Assumptions
A1: Second Coat: 12-month model, assumptions
A2: Edit the blue cells (yellow = the key levers). Every other number in the workbook is a formula.
A4: Assumption | B4: Value | C4: Note / source
A5: Demos built per week (month 1) | B5: 4 | C5: Your call. With build.js about 1–2 hrs each once research is done.
A6: Monthly growth in demos built | B6: 0.05 | C6: Assumption: gets faster as the templates mature.
A7: Weeks per month | B7: 4.33 | C7: 52 / 12
A8: Demo → paid conversion | B8: 0.125 | C8: Assumption from PLAN.md: 1 in 8 cold demos. Replace with real data after the first 20 pitches.
A9: Share of paid clients choosing Rebrand | B9: 0.25 | C9: Assumption.
A10: Refresh price (£) | B10: 500 | C10: PLAN.md price.
A11: Rebrand price (£) | B11: 1200 | C11: PLAN.md price.
A12: Share of new clients taking the Care plan | B12: 0.5 | C12: Assumption.
A13: Care plan price (£ / month) | B13: 49 | C13: PLAN.md price.
A14: Care plan monthly churn | B14: 0.03 | C14: Assumption (about 30% lost per year).
A15: Hours per demo (research + build + pitch) | B15: 2.5 | C15: Assumption with the generator pipeline.
A16: Hours to deliver a Refresh after payment | B16: 4 | C16: Intake, edits, go-live checklist.
... A22: Fixed tools and software (£ / month) | B22: 40 | C22: Assumption: Places API, email, Stripe, etc.

Sheet Model
A1: Monthly projection (£)
A3: Line | B3: M1 | C3: M2 | D3: M3 | E3: M4 | F3: M5 | G3: M6 | H3: M7 | I3: M8 | J3: M9 | K3: M10 | L3: M11 | M3: M12 | N3: Total
A4: Demos built | B4: =Assumptions!$B$5*Assumptions!$B$7*(1+Assumptions!$B$6)^0 | C4: =Assumptions!$B$5*Assumptions!$B$7*(1+Assumptions!$B$6)^1 | D4: =Assumptions!$B$5*Assumptions!$B$7*(1+Assumptions!$B$6)^2 | E4: =Assumptions!$B$5*Assumptions!$B$7*(1+Assumptions!$B$6)^3 | F4: =Assumptions!$B$5*Assumptions!$B$7*(1+Assumptions!$B$6)^4 | G4: =Assumptions!$B$5*Assumptions!$B$7*(1+Assumptions!$B$6)^5 | H4: =Assumptions!$B$5*Assumptions!$B$7*(1+Assumptions!$B$6)^6 | I4: =Assumptions!$B$5*Assumptions!$B$7*(1+Assumptions!$B$6)^7 | J4: =Assumptions!$B$5*Assumptions!$B$7*(1+Assumptions!$B$6)^8 | K4: =Assumptions!$B$5*Assumptions!$B$7*(1+Assumptions!$B$6)^9 | L4: =Assumptions!$B$5*Assumptions!$B$7*(1+Assumptions!$B$6)^10 | M4: =Assumptions!$B$5*Assumptions!$B$7*(1+Assumptions!$B$6)^11 | N4: =SUM(B4:M4)
A5: New paid clients | B5: =B4*Assumptions!$B$8 | C5: =C4*Assumptions!$B$8 | D5: =D4*Assumptions!$B$8 | E5: =E4*Assumptions!$B$8 | F5: =F4*Assumptions!$B$8 | G5: =G4*Assumptions!$B$8 | H5: =H4*Assumptions!$B$8 | I5: =I4*Assumptions!$B$8 | ... M5: =M4*Assumptions!$B$8 | N5: =SUM(B5:M5)
A6: of which Refresh | B6: =B5*(1-Assumptions!$B$9) | C6: =C5*(1-Assumptions!$B$9) | D6: =D5*(1-Assumptions!$B$9) | E6: =E5*(1-Assumptions!$B$9) | F6: =F5*(1-Assumptions!$B$9) | G6: =G5*(1-Assumptions!$B$9) | H6: =H5*(1-Assumptions!$B$9) | I6: =I5*(1-Assumptions!$B$9) | ... M6: =M5*(1-Assumptions!$B$9) | N6: =SUM(B6:M6)
A7: of which Rebrand | B7: =B5*Assumptions!$B$9 | C7: =C5*Assumptions!$B$9 | D7: =D5*Assumptions!$B$9 | E7: =E5*Assumptions!$B$9 | F7: =F5*Assumptions!$B$9 | G7: =G5*Assumptions!$B$9 | H7: =H5*Assumptions!$B$9 | I7: =I5*Assumptions!$B$9 | ... M7: =M5*Assumptions!$B$9 | N7: =SUM(B7:M7)
A8: Project revenue | B8: =B6*Assumptions!$B$10+B7*Assumptions!$B$11 | C8: =C6*Assumptions!$B$10+C7*Assumptions!$B$11 | D8: =D6*Assumptions!$B$10+D7*Assumptions!$B$11 | E8: =E6*Assumptions!$B$10+E7*Assumptions!$B$11 | F8: =F6*Assumptions!$B$10+F7*Assumptions!$B$11 | G8: =G6*Assumptions!$B$10+G7*Assumptions!$B$11 | H8: =H6*Assumptions!$B$10+H7*Assumptions!$B$11 | I8: =I6*Assumptions!$B$10+I7*Assumptions!$B$11 | ... M8: =M6*Assumptions!$B$10+M7*Assumptions!$B$11 | N8: =SUM(B8:M8)
A9: Care clients at start | B9: =0 | C9: =B12 | D9: =C12 | E9: =D12 | F9: =E12 | G9: =F12 | H9: =G12 | I9: =H12 | J9: =I12 | ... M9: =L12
A10: New care clients | B10: =B5*Assumptions!$B$12 | C10: =C5*Assumptions!$B$12 | D10: =D5*Assumptions!$B$12 | E10: =E5*Assumptions!$B$12 | F10: =F5*Assumptions!$B$12 | G10: =G5*Assumptions!$B$12 | H10: =H5*Assumptions!$B$12 | I10: =I5*Assumptions!$B$12 | ... M10: =M5*Assumptions!$B$12 | N10: =SUM(B10:M10)
A11: Care clients lost | B11: =B9*Assumptions!$B$14 | C11: =C9*Assumptions!$B$14 | D11: =D9*Assumptions!$B$14 | E11: =E9*Assumptions!$B$14 | F11: =F9*Assumptions!$B$14 | G11: =G9*Assumptions!$B$14 | H11: =H9*Assumptions!$B$14 | I11: =I9*Assumptions!$B$14 | ... M11: =M9*Assumptions!$B$14 | N11: =SUM(B11:M11)
A12: Care clients at end | B12: =B9+B10-B11 | C12: =C9+C10-C11 | D12: =D9+D10-D11 | E12: =E9+E10-E11 | F12: =F9+F10-F11 | G12: =G9+G10-G11 | H12: =H9+H10-H11 | I12: =I9+I10-I11 | ... M12: =M9+M10-M11
A13: Care revenue | B13: =B9*Assumptions!$B$13 | C13: =C9*Assumptions!$B$13 | D13: =D9*Assumptions!$B$13 | E13: =E9*Assumptions!$B$13 | F13: =F9*Assumptions!$B$13 | G13: =G9*Assumptions!$B$13 | H13: =H9*Assumptions!$B$13 | I13: =I9*Assumptions!$B$13 | ... M13: =M9*Assumptions!$B$13 | N13: =SUM(B13:M13)
A14: Total revenue | B14: =B8+B13 | C14: =C8+C13 | D14: =D8+D13 | E14: =E8+E13 | F14: =F8+F13 | G14: =G8+G13 | H14: =H8+H13 | I14: =I8+I13 | ... M14: =M8+M13 | N14: =SUM(B14:M14)
A15: Card fees | B15: =B14*Assumptions!$B$19+(B5+B9)*Assumptions!$B$20 | C15: =C14*Assumptions!$B$19+(C5+C9)*Assumptions!$B$20 | D15: =D14*Assumptions!$B$19+(D5+D9)*Assumptions!$B$20 | E15: =E14*Assumptions!$B$19+(E5+E9)*Assumptions!$B$20 | F15: =F14*Assumptions!$B$19+(F5+F9)*Assumptions!$B$20 | G15: =G14*Assumptions!$B$19+(G5+G9)*Assumptions!$B$20 | H15: =H14*Assumptions!$B$19+(H5+H9)*Assumptions!$B$20 | I15: =I14*Assumptions!$B$19+(I5+I9)*Assumptions!$B$20 | ... M15: =M14*Assumptions!$B$19+(M5+M9)*Assumptions!$B$20 | N15: =SUM(B15:M15)
A16: Hosting + domains | B16: =B12*Assumptions!$B$21 | C16: =C12*Assumptions!$B$21 | D16: =D12*Assumptions!$B$21 | E16: =E12*Assumptions!$B$21 | F16: =F12*Assumptions!$B$21 | G16: =G12*Assumptions!$B$21 | H16: =H12*Assumptions!$B$21 | I16: =I12*Assumptions!$B$21 | ... M16: =M12*Assumptions!$B$21 | N16: =SUM(B16:M16)
A17: Tools | B17: =Assumptions!$B$22 | C17: =Assumptions!$B$22 | D17: =Assumptions!$B$22 | E17: =Assumptions!$B$22 | F17: =Assumptions!$B$22 | G17: =Assumptions!$B$22 | H17: =Assumptions!$B$22 | I17: =Assumptions!$B$22 | ... M17: =Assumptions!$B$22 | N17: =SUM(B17:M17)
A18: Total costs | B18: =B15+B16+B17 | C18: =C15+C16+C17 | D18: =D15+D16+D17 | E18: =E15+E16+E17 | F18: =F15+F16+F17 | G18: =G15+G16+G17 | H18: =H15+H16+H17 | I18: =I15+I16+I17 | ... M18: =M15+M16+M17 | N18: =SUM(B18:M18)
A19: Profit | B19: =B14-B18 | C19: =C14-C18 | D19: =D14-D18 | E19: =E14-E18 | F19: =F14-F18 | G19: =G14-G18 | H19: =H14-H18 | I19: =I14-I18 | ... M19: =M14-M18 | N19: =SUM(B19:M19)
A20: Cumulative profit | B20: =B19 | C20: =B20+C19 | D20: =C20+D19 | E20: =D20+E19 | F20: =E20+F19 | G20: =F20+G19 | H20: =G20+H19 | I20: =H20+I19 | J20: =I20+J19 | ... M20: =L20+M19
A21: Hours worked | B21: =B4*Assumptions!$B$15+B6*Assumptions!$B$16+B7*Assumptions!$B$17+B9*Assumptions!$B$18 | C21: =C4*Assumptions!$B$15+C6*Assumptions!$B$16+C7*Assumptions!$B$17+C9*Assumptions!$B$18 | D21: =D4*Assumptions!$B$15+D6*Assumptions!$B$16+D7*Assumptions!$B$17+D9*Assumptions!$B$18 | E21: =E4*Assumptions!$B$15+E6*Assumptions!$B$16+E7*Assumptions!$B$17+E9*Assumptions!$B$18 | F21: =F4*Assumptions!$B$15+F6*Assumptions!$B$16+F7*Assumptions!$B$17+F9*Assumptions!$B$18 | G21: =G4*Assumptions!$B$15+G6*Assumptions!$B$16+G7*Assumptions!$B$17+G9*Assumptions!$B$18 | H21: =H4*Assumptions!$B$15+H6*Assumptions!$B$16+H7*Assumptions!$B$17+H9*Assumptions!$B$18 | I21: =I4*Assumptions!$B$15+I6*Assumptions!$B$16+I7*Assumptions!$B$17+I9*Assumptions!$B$18 | ... M21: =M4*Assumptions!$B$15+M6*Assumptions!$B$16+M7*Assumptions!$B$17+M9*Assumptions!$B$18 | N21: =SUM(B21:M21)
A22: Effective £ per hour | B22: =IF(B21>0,B19/B21,0) | C22: =IF(C21>0,C19/C21,0) | D22: =IF(D21>0,D19/D21,0) | E22: =IF(E21>0,E19/E21,0) | F22: =IF(F21>0,F19/F21,0) | G22: =IF(G21>0,G19/G21,0) | H22: =IF(H21>0,H19/H21,0) | I22: =IF(I21>0,I19/I21,0) | ... N22: =IF(N21>0,N19/N21,0)
A23: Monthly recurring revenue (end) | B23: =B12*Assumptions!$B$13 | C23: =C12*Assumptions!$B$13 | D23: =D12*Assumptions!$B$13 | E23: =E12*Assumptions!$B$13 | F23: =F12*Assumptions!$B$13 | G23: =G12*Assumptions!$B$13 | H23: =H12*Assumptions!$B$13 | I23: =I12*Assumptions!$B$13 | ... M23: =M12*Assumptions!$B$13
A26: Care revenue is billed on clients at the start of each month. Fractional clients are averages (expected values), not literal half-clients.
