Workbook

Sheet Invoice
B2: INVOICE
B4: =Settings!C4 -> Your Business Name | E4: Invoice # | F4: INV-001
B5: =Settings!C5 -> 1 Your Street | E5: Date | F5: 46204
B6: =Settings!C6 -> Your Town, Postcode | E6: Due | F6: =F5+Settings!C9 -> 46218
B7: =Settings!C7 -> you@example.com · 07000 000000
B9: BILL TO
B10: Client Company Ltd
B11: 1 Client Street
B12: Town, Postcode
B14: Description | C14: Qty | D14: Unit price (£) | E14: Line total (£)
B15: Design work — homepage | C15: 3 | D15: 150 | E15: =IF(B15="","",N(C15)*N(D15)) -> 450
B16: Hosting setup | C16: 1 | D16: 200 | E16: =IF(B16="","",N(C16)*N(D16)) -> 200
E17: =IF(B17="","",N(C17)*N(D17))
E18: =IF(B18="","",N(C18)*N(D18))
E19: =IF(B19="","",N(C19)*N(D19))
E20: =IF(B20="","",N(C20)*N(D20))
E21: =IF(B21="","",N(C21)*N(D21))
E22: =IF(B22="","",N(C22)*N(D22))
E23: =IF(B23="","",N(C23)*N(D23))
E24: =IF(B24="","",N(C24)*N(D24))
E25: =IF(B25="","",N(C25)*N(D25))
E26: =IF(B26="","",N(C26)*N(D26))
D28: Subtotal | E28: =SUM(E15:E26) -> 650
D29: ="VAT ("&TEXT(Settings!C10,"0%")&")" -> VAT (20%) | E29: =E28*Settings!C10 -> 130
D30: TOTAL | E30: =E28+E29 -> 780
B32: =Settings!C8 -> Sort 00-00-00 · Account 00000000 · Ref: invoice number
B33: ="Payment due within "&Settings!C9&" days of invoice date." -> Payment due within 14 days of invoice date.

Sheet Settings
B2: SETTINGS — fill the yellow cells once
B4: Business name | C4: Your Business Name | D4: Shown at the top of every invoice.
B5: Address line 1 | C5: 1 Your Street
B6: Address line 2 | C6: Your Town, Postcode
B7: Email / phone | C7: you@example.com · 07000 000000
B8: Bank details line | C8: Sort 00-00-00 · Account 00000000 · Ref: invoice number | D8: Shown at the bottom of the invoice.
B9: Payment terms (days) | C9: 14 | D9: Due date = invoice date + this.
B10: VAT rate | C10: 0.2 | D10: Set to 0 if you're not VAT-registered.
B12: Tip: duplicate the Invoice tab for each new invoice and bump the invoice number.
